langchain_deeplake/__init__.py
langchain_deeplake/distance_metric.py
langchain_deeplake/exceptions.py
langchain_deeplake/filtering_util.py
langchain_deeplake/py.typed
langchain_deeplake/query.py
langchain_deeplake/vectorstores.py
langchain_deeplake-0.1.0.dist-info/LICENSE
langchain_deeplake-0.1.0.dist-info/METADATA
langchain_deeplake-0.1.0.dist-info/WHEEL
langchain_deeplake-0.1.0.dist-info/RECORD
