Metadata-Version: 2.1
Name: langchain-deeplake
Version: 0.1.0
Summary: An integration package connecting Deeplake and LangChain
Home-page: https://github.com/activeloopai/langchain-deeplake
License: MIT
Author: activeloop.ai
Author-email: support@activeloop.ai
Requires-Python: >=3.8,<4.0
Classifier: License :: OSI Approved :: MIT License
Classifier: Programming Language :: Python :: 3
Classifier: Programming Language :: Python :: 3.8
Classifier: Programming Language :: Python :: 3.9
Classifier: Programming Language :: Python :: 3.10
Classifier: Programming Language :: Python :: 3.11
Classifier: Programming Language :: Python :: 3.12
Classifier: Programming Language :: Python :: 3.13
Requires-Dist: deeplake (>=4.1)
Requires-Dist: langchain-core (>=0.2.43)
Project-URL: Repository, https://github.com/activeloopai/langchain-deeplake
